README
setup.py
jump2/__init__.py
jump2/pool.py
jump2.egg-info/PKG-INFO
jump2.egg-info/SOURCES.txt
jump2.egg-info/dependency_links.txt
jump2.egg-info/top_level.txt
jump2/analysis/__init__.py
jump2/analysis/ExtractAbinit/__init__.py
jump2/analysis/ExtractGuassian/__init__.py
jump2/analysis/ExtractGulp/__init__.py
jump2/analysis/ExtractLammps/__init__.py
jump2/analysis/ExtractPwscf/__init__.py
jump2/analysis/ExtractVasp/__init__.py
jump2/analysis/ExtractVasp/basic.py
jump2/analysis/ExtractVasp/basics.py
jump2/analysis/ExtractVasp/extract_aphonon.py
jump2/analysis/ExtractVasp/extract_band.py
jump2/analysis/ExtractVasp/extract_dos.py
jump2/analysis/ExtractVasp/extract_structurefactors.py
jump2/analysis/ExtractVasp/getband.py
jump2/analysis/ExtractVasp/pdos.py
jump2/analysis/ExtractVasp/plot.py
jump2/analysis/ExtractVasp/vasp_analysis.py
jump2/analysis/ExtractVasp/xdatcar.py
jump2/config/__init__.py
jump2/config/cluster.py
jump2/db/__init__.py
jump2/db/manager.py
jump2/db/settings.py
jump2/db/urls.py
jump2/db/wsgi.py
jump2/db/cache/__init__.py
jump2/db/cache/cachedCompositionProvider.py
jump2/db/cache/cachedElementProvider.py
jump2/db/cache/cachedMolCompositionProvider.py
jump2/db/cache/cachedMolElementProvider.py
jump2/db/cache/cachedOperationProvider.py
jump2/db/cache/cachedSpacegroupProvider.py
jump2/db/cache/cachedSpeciesProvider.py
jump2/db/iostream/__init__.py
jump2/db/iostream/cif.py
jump2/db/iostream/hall2hm.py
jump2/db/iostream/read.py
jump2/db/iostream/spaceGroupD3.py
jump2/db/iostream/write.py
jump2/db/materials/__init__.py
jump2/db/materials/admin.py
jump2/db/materials/apps.py
jump2/db/materials/atom.py
jump2/db/materials/case.py
jump2/db/materials/composition.py
jump2/db/materials/element.py
jump2/db/materials/models.py
jump2/db/materials/molAtom.py
jump2/db/materials/molComposition.py
jump2/db/materials/molElement.py
jump2/db/materials/molStructure.py
jump2/db/materials/prototype.py
jump2/db/materials/site.py
jump2/db/materials/spacegroup.py
jump2/db/materials/species.py
jump2/db/materials/structure.py
jump2/db/materials/structureFactory.py
jump2/db/materials/tests.py
