Metadata-Version: 1.2
Name: jump2
Version: 1.0
Summary: Python Package for High Throughput                Materials-design calculation.
Home-page: UNKNOWN
Author: jump2 team
Author-email: lijun_zhang@jlu.edu.cn
Maintainer: Xin-Gang Zhao, Yuhao Fu, Guangren Na, Shulin Luo
Maintainer-email: xgzhao0201@gmail.com,                  fuyuhaoy@gmail.com,                  guangrenna@gmail.com,                  shulinluo999@gmail.com
License: Jilin University, Version 1.0
Platform: Linux
